pyprintplus/__init__.py
pyprintplus/log.py
pyprintplus-1.0.4.dist-info/LICENSE
pyprintplus-1.0.4.dist-info/METADATA
pyprintplus-1.0.4.dist-info/WHEEL
pyprintplus-1.0.4.dist-info/top_level.txt
pyprintplus-1.0.4.dist-info/RECORD
