Metadata-Version: 2.1
Name: pyprintplus
Version: 1.0.4
Summary: A better way of printing logs in Python.
Home-page: https://github.com/glowingkitty/PyPrintPlus
Author: Marco
License: UNKNOWN
Platform: UNKNOWN
Classifier: Programming Language :: Python :: 3
Classifier: License :: OSI Approved :: MIT License
Classifier: Operating System :: OS Independent
Requires-Python: >=3.6
